dev_studio/__init__.py
dev_studio/gui.py
dev_studio/flow/__init__.py
dev_studio/flow/custom_home/__init__.py
dev_studio/flow/demo_project/__init__.py
dev_studio/flow/demo_project/maya_startup/__init__.py
dev_studio/flow/demo_project/maya_startup/userSetup.py
dev_studio/flow/unittest_project/__init__.py
dev_studio/flow/unittest_project/icon_browser/__init__.py
dev_studio/flow/unittest_project/showcase/__init__.py
dev_studio/flow/unittest_project/showcase/action_context.py
dev_studio/flow/unittest_project/showcase/action_submenus_demo.py
dev_studio/flow/unittest_project/showcase/actions.py
dev_studio/flow/unittest_project/showcase/custom_page.py
dev_studio/flow/unittest_project/showcase/editors.py
dev_studio/flow/unittest_project/showcase/injection.py
dev_studio/flow/unittest_project/showcase/map_as_view.py
dev_studio/flow/unittest_project/showcase/maps.py
dev_studio/flow/unittest_project/showcase/other.py
dev_studio/flow/unittest_project/showcase/relations.py
dev_studio/flow/unittest_project/showcase/ui_config.py
dev_studio/flow/unittest_project/showcase/values.py
dev_studio/icons/__init__.py
dev_studio/icons/flow/__init__.py
dev_studio/icons/gui/__init__.py
dev_studio/icons/gui/kabaret_icon.png
kabaret/__init__.py
kabaret/app/__init__.py
kabaret/app/_actor.py
kabaret/app/plugin_manager.py
kabaret/app/resources.py
kabaret/app/session.py
kabaret/app/actors/__init__.py
kabaret/app/actors/cluster.py
kabaret/app/actors/default_actors_plugin.py
kabaret/app/actors/flow/__init__.py
kabaret/app/actors/flow/actor.py
kabaret/app/actors/flow/generic_home_flow.py
kabaret/app/actors/flow/utils.py
kabaret/app/actors/flow/value_store.py
kabaret/app/ui/__init__.py
kabaret/app/ui/view.py
kabaret/app/ui/gui/__init__.py
kabaret/app/ui/gui/embedded.py
kabaret/app/ui/gui/standalone.py
kabaret/app/ui/gui/icons/__init__.py
kabaret/app/ui/gui/icons/flow/3dsmax.png
kabaret/app/ui/gui/icons/flow/__init__.py
kabaret/app/ui/gui/icons/flow/action.png
kabaret/app/ui/gui/icons/flow/afterfx.png
kabaret-2.2.0.dist-info/AUTHORS
kabaret-2.2.0.dist-info/LICENSE
kabaret-2.2.0.dist-info/METADATA
kabaret-2.2.0.dist-info/WHEEL
kabaret-2.2.0.dist-info/top_level.txt
kabaret-2.2.0.dist-info/RECORD
