Metadata-Version: 2.1
Name: kabaret
Version: 2.2.0
Summary: VFX/Animation Studio Framework
Home-page: http://www.kabaretstudio.com
Author: Damien dee Coureau
Author-email: kabaret-dev@googlegroups.com
License: LGPLv3+
Keywords: vfx animation framewok dataflow workflow asset manager production tracker
Classifier: Development Status :: 5 - Production/Stable
Classifier: Topic :: Software Development :: Libraries :: Application Frameworks
Classifier: Topic :: Desktop Environment :: File Managers
Classifier: Topic :: Multimedia :: Graphics
Classifier: Topic :: Office/Business :: Groupware
Classifier: Topic :: Office/Business :: Scheduling
Classifier: Intended Audience :: Developers
Classifier: Intended Audience :: End Users/Desktop
Classifier: Intended Audience :: Information Technology
Classifier: Operating System :: OS Independent
Classifier: Programming Language :: Python :: 2.7
Classifier: Programming Language :: Python :: 3.3
Classifier: License :: OSI Approved :: GNU Lesser General Public License v3 or later (LGPLv3+)
Requires-Python: >=2.7,!=3.0.*,!=3.1.*,!=3.2.*
License-File: LICENSE
License-File: AUTHORS
Requires-Dist: pluggy
Requires-Dist: redis
Requires-Dist: six
Requires-Dist: qtpy
